CHANGELOG.rst
MANIFEST.in
README.rst
dev-requirements.txt
requirements.txt
setup.py
tox.ini
proto_schematics/__init__.py
proto_schematics/converters.py
proto_schematics/models.py
proto_schematics/types.py
proto_schematics.egg-info/PKG-INFO
proto_schematics.egg-info/SOURCES.txt
proto_schematics.egg-info/dependency_links.txt
proto_schematics.egg-info/not-zip-safe
proto_schematics.egg-info/requires.txt
proto_schematics.egg-info/top_level.txt
tests/__init__.py