Metadata-Version: 1.1
Name: proto-schematics
Version: 0.1.0
Summary: Converts protobuf generated messages to Python friendly schematics models.
Home-page: https://github.com/loggi/proto-schematics
Author: Gabriela Surita
Author-email: gsurita@loggi.com
License: Apache License (2.0)
Keywords: loggi,schematics,protobuf,grpc
Platform: UNKNOWN
Classifier: Intended Audience :: Developers
Classifier: Operating System :: OS Independent
Classifier: Programming Language :: Python
Classifier: Programming Language :: Python :: 2
Classifier: Programming Language :: Python :: 2.7
Classifier: Programming Language :: Python :: 3
Classifier: Programming Language :: Python :: 3.4
Classifier: Programming Language :: Python :: 3.5
Classifier: Programming Language :: Python :: 3.6
